nc_mis/__init__.py
nc_mis/drivers/__init__.py
nc_mis/drivers/abstract.py
nc_mis/drivers/aruba/__init__.py
nc_mis/drivers/aruba/aos/AOS.py
nc_mis/drivers/aruba/aos/__init__.py
nc_mis/drivers/aruba/aos/ttp_templates/show_run.ttp
nc_mis/drivers/fs/fs.py
nc_mis/drivers/fs/ttp_templates/show_run.ttp
nc_mis/drivers/hp/__init__.py
nc_mis/drivers/hp/procurve.py
nc_mis/drivers/hp/ttp_templates/show_run.ttp
nc_mis/drivers/juniper/JUNOS.py
nc_mis/drivers/juniper/__init__.py
nc_mis/drivers/juniper/templates/interface.j2
nc_mis/scripts/acl.py
nc_mis/scripts/backup.py
nc_mis/scripts/base.py
nc_mis/scripts/health.py
nc_mis/scripts/logging.py
nc_mis/scripts/radius.py
nc_mis/scripts/vlan_config.py
nc_mis/tests/__init__.py
nc_mis/tests/test_drivers.py
nc_mis/tests/drivers/aos.py
nc_mis/tests/drivers/juniper.py
nc_mis-0.2.3.dist-info/LICENSE
nc_mis-0.2.3.dist-info/METADATA
nc_mis-0.2.3.dist-info/WHEEL
nc_mis-0.2.3.dist-info/top_level.txt
nc_mis-0.2.3.dist-info/RECORD
